{
    "identifier" : "banner01",
    "name" : "Banner para twitter",
    "description": "Eu amo esses fundos com formas geométricas",
    "artist" : [
        "bernacha"
    ],
    "path_light" : "banner",
    "path_dark" : null,
    "is_banner" : true,
    "path_card_light" : "card",
    "path_card_dark" : null,
    "created_at" : "2024/06/16",
    "personas" : [
        "uotlaf"
    ],
    "tags" : [
        "floating",
        "geometric_forms",
        "memphis_aesthetic",
        "bold_colors"
    ],
    "links" : {
    }
}
